picachooser/LightboxItem.py
picachooser/__init__.py
picachooser/_version.py
picachooser/colormaps.py
picachooser/fit.py
picachooser/graderTemplate.py
picachooser/graderTemplate_qt6.py
picachooser/io.py
picachooser/melodicompTemplate.py
picachooser/melodicompTemplate_qt6.py
picachooser/picachooserTemplate.py
picachooser/picachooserTemplate_qt6.py
picachooser/picachooser_imonlyTemplate.py
picachooser/picachooser_imonlyTemplate_qt6.py
picachooser/rtgraderTemplate.py
picachooser/rtgraderTemplate_qt6.py
picachooser/stats.py
picachooser/util.py
picachooser/data/reference/Smith_D50_Subset_ICs.nii.gz
picachooser/scripts/PICAchooser.py
picachooser/scripts/PICAchooser_dispatcher.py
picachooser/scripts/grader.py
picachooser/scripts/melodicomp.py
picachooser/scripts/rtgrader.py
picachooser-1.5.2.dist-info/licenses/LICENSE
picachooser-1.5.2.dist-info/METADATA
picachooser-1.5.2.dist-info/WHEEL
picachooser-1.5.2.dist-info/entry_points.txt
picachooser-1.5.2.dist-info/top_level.txt
picachooser-1.5.2.dist-info/RECORD
