Metadata-Version: 2.4
Name: picachooser
Version: 1.5.2
Summary: Lightweight GUI for sorting, classifying, and matching MELODIC ICA components.
Author-email: Blaise Frederick <blaise.frederick@gmail.com>
License: Apache Software License
Project-URL: Homepage, https://github.com/bbfrederick/picachooser
Project-URL: Bug Tracker, https://github.com/bbfrederick/picachooser/issues
Project-URL: Repository, https://github.com/bbfrederick/picachooser.git
Project-URL: Documentation, https://picachooser.readthedocs.io
Project-URL: Changelog, https://github.com/bbfrederick/picachooser/blob/main/CHANGELOG.md
Keywords: fMRI,ICA,component matching,visualization
Classifier: Operating System :: OS Independent
Classifier: Development Status :: 5 - Production/Stable
Classifier: Intended Audience :: Science/Research
Classifier: Topic :: Scientific/Engineering :: Image Recognition
Classifier: License :: OSI Approved :: Apache Software License
Classifier: Programming Language :: Python :: 3.9
Classifier: Programming Language :: Python :: 3.10
Classifier: Programming Language :: Python :: 3.11
Classifier: Programming Language :: Python :: 3.12
Requires-Python: >=3.9
License-File: LICENSE
Requires-Dist: numpy
Requires-Dist: scipy
Requires-Dist: pandas
Requires-Dist: nibabel
Requires-Dist: pyqtgraph>=0.13.4
Requires-Dist: pyqt6-sip
Requires-Dist: pyqt6
Requires-Dist: pillow
Provides-Extra: test
Requires-Dist: codecov; extra == "test"
Requires-Dist: coverage; extra == "test"
Requires-Dist: coveralls; extra == "test"
Requires-Dist: flake8-black; extra == "test"
Requires-Dist: pytest; extra == "test"
Requires-Dist: pytest-cov; extra == "test"
Provides-Extra: doc
Requires-Dist: sphinx; extra == "doc"
Requires-Dist: sphinx_rtd_theme; extra == "doc"
Requires-Dist: sphinx-argparse; extra == "doc"
Requires-Dist: sphinx-gallery; extra == "doc"
Requires-Dist: myst-parser; extra == "doc"
Requires-Dist: numpydoc; extra == "doc"
Requires-Dist: sphinxcontrib-bibtex; extra == "doc"
Requires-Dist: tomlkit; extra == "doc"
Dynamic: license-file
